LICENSE
MANIFEST.in
README.rst
setup.py
django_inspectdb.egg-info/PKG-INFO
django_inspectdb.egg-info/SOURCES.txt
django_inspectdb.egg-info/dependency_links.txt
django_inspectdb.egg-info/not-zip-safe
django_inspectdb.egg-info/top_level.txt
inspectdb/__init__.py
inspectdb/helpers.py
inspectdb/management/__init__.py
inspectdb/management/commands/__init__.py
inspectdb/management/commands/inspectdb.py