Metadata-Version: 1.0
Name: django-inspectdb
Version: 0.2
Summary: Better inspectdb.
Home-page: https://github.com/aino/django-inspectdb
Author: Mikko Hellsing
Author-email: mikko@aino.se
License: BSD
Platform: UNKNOWN
Classifier: Development Status :: 3 - Alpha
Classifier: Environment :: Web Environment
Classifier: Intended Audience :: Developers
Classifier: License :: OSI Approved :: BSD License
Classifier: Operating System :: OS Independent
Classifier: Programming Language :: Python
Classifier: Topic :: Internet :: WWW/HTTP :: Dynamic Content
Classifier: Framework :: Django
